{
  "source": {
      "includePattern": ".+\\.js(doc|x)?$",
      "include": ["README.md", "./lib"]
  },
  "recurseDepth": 3,
  "opts": {
      "destination": "./docs/",
      "recurse": true
  },
  "plugins" : ["plugins/staticFiles/staticFiles.cjs"],
  "staticFiles": {
    "include": ["static:./build/docs/css", "img:./build/docs/img"]
  },
  "templates": {
    "systemName"            : "J5e",
    "systemSummary"         : "Johnny Five for Embedded Systems",
    "systemLogo"            : "./build/docs/favicon/j5e.png",
    "forkMe"                : "./build/docs/fork/forkme_right_white_ffffff.webp",
    "systemColor"           : "#000",
    "copyright"             : "Copyright © 2019—2020 The contributors to the j5e and Johnny-Five projects.",
    "dateFormat"            : "MMMM D, YYYY",
    "showAccessFilter"      : true,
    "inlineNav"             : true,
    "includeDate"           : false,
    "navMembers"            : [
                                {"kind": "module", "title": "Modules", "summary": "All documented modules."},
                                {"kind": "class", "title": "Classes", "summary": "All documented classes."},
                                {"kind": "external", "title": "Externals", "summary": "All documented external members."},
                                {"kind": "global", "title": "Globals", "summary": "All documented globals."},
                                {"kind": "mixin", "title": "Mixins", "summary": "All documented mixins."},
                                {"kind": "interface", "title": "Interfaces", "summary": "All documented interfaces."},
                                {"kind": "tutorial", "title": "Tutorials", "summary": "All available tutorials."}
                              ],
    "analytics"             : { "ua": "UA-36026876-4", "domain": "dtex.github.io" },
    "favicon"               : "./build/docs/favicon/j5e.png",
    "stylesheets"           : ["./static/custom.css"]
  }
}